speedport/__init__.py
speedport/__main__.py
speedport/api.py
speedport/call.py
speedport/connection.py
speedport/const.py
speedport/device.py
speedport/exceptions.py
speedport/speedport.py
speedport_api-0.6.0.dist-info/LICENSE
speedport_api-0.6.0.dist-info/METADATA
speedport_api-0.6.0.dist-info/WHEEL
speedport_api-0.6.0.dist-info/entry_points.txt
speedport_api-0.6.0.dist-info/top_level.txt
speedport_api-0.6.0.dist-info/RECORD
