Metadata-Version: 2.1
Name: speedport-api
Version: 0.6.0
Summary: Control Telekom Speedport routers with Python
Author: Andre Basche
License: MIT
Project-URL: GitHub, https://github.com/Andre0512/speedport-api
Project-URL: PyPI, https://pypi.org/project/speedport-api
Platform: any
Classifier: Development Status :: 4 - Beta
Classifier: Environment :: Console
Classifier: License :: OSI Approved :: MIT License
Classifier: Natural Language :: English
Classifier: Operating System :: OS Independent
Classifier: Programming Language :: Python :: 3.8
Classifier: Programming Language :: Python :: 3.9
Classifier: Programming Language :: Python :: 3.10
Classifier: Programming Language :: Python :: 3.11
Classifier: Programming Language :: Python :: 3.12
Classifier: Topic :: Software Development :: Libraries :: Python Modules
Requires-Python: >=3.8
License-File: LICENSE
Requires-Dist: aiohttp >=3.8
Requires-Dist: pycryptodome >=3.18
